chibi/__init__.py
chibi/b64.py
chibi/module.py
chibi/nix.py
chibi/parser.py
chibi/atlas/__init__.py
chibi/chain/__init__.py
chibi/config/__init__.py
chibi/config/config.py
chibi/config/logger.py
chibi/fancy/__init__.py
chibi/fancy/is_type.py
chibi/file/__init__.py
chibi/file/file.py
chibi/file/image.py
chibi/file/path.py
chibi/file/snippets.py
chibi/file/temp.py
chibi/file/other/__init__.py
chibi/file/other/chibi_csv.py
chibi/file/other/chibi_json.py
chibi/file/other/chibi_python.py
chibi/file/other/chibi_systemd.py
chibi/file/other/chibi_yaml.py
chibi/file/other/conf.py
chibi/madness/__init__.py
chibi/madness/byte.py
chibi/madness/file.py
chibi/madness/string.py
chibi/metaphors/__init__.py
chibi/metaphors/book.py
chibi/net/__init__.py
chibi/net/hostname.py
chibi/net/network/__init__.py
chibi/net/network/interface.py
chibi/net/network_manager/__init__.py
chibi/object/__init__.py
chibi/object/descriptor.py
chibi/object/object.py
chibi/pipeline/__init__.py
chibi/pipeline/pipeline.py
chibi/pipeline/xml.py
chibi/snippet/__init__.py
chibi/snippet/dict.py
chibi/snippet/extra_string.py
chibi/snippet/file.py
chibi/snippet/func.py
chibi/snippet/image.py
chibi/snippet/is_type.py
chibi/snippet/iter.py
chibi/snippet/list.py
chibi/snippet/regex.py
chibi/snippet/string.py
chibi/snippet/table.py
chibi/snippet/xml.py
chibi/units/__init__.py
chibi/units/base.py
chibi/units/prefix.py
chibi/units/si.py
chibi-0.17.0.dist-info/licenses/AUTHORS.rst
chibi-0.17.0.dist-info/licenses/LICENSE
chibi-0.17.0.dist-info/METADATA
chibi-0.17.0.dist-info/WHEEL
chibi-0.17.0.dist-info/top_level.txt
chibi-0.17.0.dist-info/RECORD
