Metadata-Version: 2.4
Name: chibi
Version: 0.17.0
Summary: python snippets and other useful things
Home-page: https://github.com/dem4ply/chibi
Author: dem4ply
Author-email: dem4ply@gmail.com
License: WTFPL
Keywords: chibi
Classifier: Development Status :: 5 - Production/Stable
Classifier: Intended Audience :: Developers
Classifier: License :: Public Domain
Classifier: Natural Language :: English
Classifier: Natural Language :: Spanish
Classifier: Programming Language :: Python :: 3.7
Classifier: Programming Language :: Python :: 3.8
Classifier: Programming Language :: Python :: 3.9
Classifier: Programming Language :: Python :: 3.10
Classifier: Programming Language :: Python :: 3.11
Classifier: Programming Language :: Python :: 3.12
Classifier: Programming Language :: Python :: 3.13
Classifier: Programming Language :: Python :: 3.14
Classifier: Topic :: Utilities
License-File: LICENSE
License-File: AUTHORS.rst
Requires-Dist: python-magic>=0.4.15
Requires-Dist: dateutils>=0.6.6
Requires-Dist: xmltodict>=0.12.0
Requires-Dist: pyyaml>=5.1.2
Requires-Dist: chibi-donkey>=1.0.1
Requires-Dist: chibi-atlas>=1.0.2
Dynamic: author
Dynamic: author-email
Dynamic: classifier
Dynamic: description
Dynamic: home-page
Dynamic: keywords
Dynamic: license
Dynamic: license-file
Dynamic: requires-dist
Dynamic: summary
